[
    {"img":"./imgs/giftShow (1).jpg","name":"礼品 · 999纯金箔玫瑰+陶瓷花瓶","price":"¥138","sell":"已售 3.5万 件"},
    {"img":"./imgs/giftShow (2).jpg","name":"礼品 · 桃李满门/满天下","price":"¥378","sell":"已售 1589 件"},
    {"img":"./imgs/giftShow (3).jpg","name":"礼品 · 迪奥口红#999+迪奥花漾淡香水30ml","price":"¥899","sell":"已售 177 件"},
    {"img":"./imgs/giftShow (4).jpg","name":"礼品 · 施华洛世奇DAZZLING SWAN天鹅项链 ","price":"¥988","sell":"已售 43 件"},
    {"img":"./imgs/giftShow (5).jpg","name":"礼品 · 星期耳钉礼盒","price":"¥239","sell":"已售 1974 件"},
    {"img":"./imgs/giftShow (6).jpg","name":"礼品 · T400双C银项链女纯银锁骨链镶施华洛世奇锆","price":"¥259","sell":"已售 301 件"},
    {"img":"./imgs/giftShow (7).jpg","name":"礼品 · 施华洛世奇ONE系列爱心项链+耳钉套装/镀玫瑰金色","price":"¥1359","sell":"已售 53 件"},
    {"img":"./imgs/giftShow (8).jpg","name":"礼品 · woody书灯木质led折叠usb书本灯-时尚版（黑胡桃）","price":"¥198","sell":"已售 448 件"},
    {"img":"./imgs/giftShow (9).jpg","name":"礼品 · Woody创意木质3D灯之风车系列","price":"¥158","sell":"已售 168 件"},
    {"img":"./imgs/giftShow (10).jpg","name":"礼品 · 猫王收音机MW-PVX野性迷你便携蓝牙户外音箱/沙漠黄","price":"¥439","sell":"已售 52 件"}
]